setup.py
ebe/__init__.py
ebe/ebe.py
ebe.egg-info/PKG-INFO
ebe.egg-info/SOURCES.txt
ebe.egg-info/dependency_links.txt
ebe.egg-info/top_level.txt